<cards releaseDate="2000-06-05T00:00:00" code="PCY">
  <item>
    <id>PCY0001</id>
    <colors>
      <color>W</color>
    </colors>
    <rarity>U</rarity>
    <cost>{1}{W}{W}</cost>
    <type>INS</type>
    <characteristics>
    </characteristics>
    <artist>Kev Walker</artist>
    <style>PRE_8</style>
    <imagePath>Abolish.jpg</imagePath>
    <bgimagepathLarge>bg_PRE_8_W_Large.png</bgimagepathLarge>
    <bgimagepathSmall>bg_PRE_8_W_Small.png</bgimagepathSmall>
  </item>
  <item>
    <id>PCY0002</id>
    <colors>
      <color>W</color>
    </colors>
    <rarity>C</rarity>
    <cost>{2}{W}</cost>
    <type>ENC</type>
    <characteristics>
    </characteristics>
    <artist>Rebecca Guay</artist>
    <style>PRE_8</style>
    <imagePath>Aura Fracture.jpg</imagePath>
    <bgimagepathLarge>bg_PRE_8_W_Large.png</bgimagepathLarge>
    <bgimagepathSmall>bg_PRE_8_W_Small.png</bgimagepathSmall>
  </item>
  <item>
    <id>PCY0003</id>
    <colors>
      <color>W</color>
    </colors>
    <rarity>R</rarity>
    <cost>{6}{W}{W}</cost>
    <type>CRE</type>
    <characteristics>4/9</characteristics>
    <artist>rk post</artist>
    <style>PRE_8</style>
    <imagePath>Avatar of Hope.jpg</imagePath>
    <bgimagepathLarge>bg_PRE_8_W_Large.png</bgimagepathLarge>
    <bgimagepathSmall>bg_PRE_8_W_Small.png</bgimagepathSmall>
  </item>
  <item>
    <id>PCY0004</id>
    <colors>
      <color>W</color>
    </colors>
    <rarity>R</rarity>
    <cost>{7}{W}{W}</cost>
    <type>SOR</type>
    <characteristics>
    </characteristics>
    <artist>Anthony S. Waters</artist>
    <style>PRE_8</style>
    <imagePath>Blessed Wind.jpg</imagePath>
    <bgimagepathLarge>bg_PRE_8_W_Large.png</bgimagepathLarge>
    <bgimagepathSmall>bg_PRE_8_W_Small.png</bgimagepathSmall>
  </item>
  <item>
    <id>PCY0005</id>
    <colors>
      <color>W</color>
    </colors>
    <rarity>R</rarity>
    <cost>{2}{W}{W}</cost>
    <type>ENC</type>
    <characteristics>
    </characteristics>
    <artist>Ray Lago</artist>
    <style>PRE_8</style>
    <imagePath>Celestial Convergence.jpg</imagePath>
    <bgimagepathLarge>bg_PRE_8_W_Large.png</bgimagepathLarge>
    <bgimagepathSmall>bg_PRE_8_W_Small.png</bgimagepathSmall>
  </item>
  <item>
    <id>PCY0006</id>
    <colors>
      <color>W</color>
    </colors>
    <rarity>C</rarity>
    <cost>{1}{W}{W}</cost>
    <type>CRE</type>
    <characteristics>2/2</characteristics>
    <artist>John Howe</artist>
    <style>PRE_8</style>
    <imagePath>Diving Griffin.jpg</imagePath>
    <bgimagepathLarge>bg_PRE_8_W_Large.png</bgimagepathLarge>
    <bgimagepathSmall>bg_PRE_8_W_Small.png</bgimagepathSmall>
  </item>
  <item>
    <id>PCY0007</id>
    <colors>
      <color>W</color>
    </colors>
    <rarity>U</rarity>
    <cost>{2}{W}{W}</cost>
    <type>ENC</type>
    <characteristics>
    </characteristics>
    <artist>D. Alexander Gregory</artist>
    <style>PRE_8</style>
    <imagePath>Entangler.jpg</imagePath>
    <bgimagepathLarge>bg_PRE_8_W_Large.png</bgimagepathLarge>
    <bgimagepathSmall>bg_PRE_8_W_Small.png</bgimagepathSmall>
  </item>
  <item>
    <id>PCY0008</id>
    <colors>
      <color>W</color>
    </colors>
    <rarity>C</rarity>
    <cost>{X}{W}</cost>
    <type>INS</type>
    <characteristics>
    </characteristics>
    <artist>Joel Biske</artist>
    <style>PRE_8</style>
    <imagePath>Excise.jpg</imagePath>
    <bgimagepathLarge>bg_PRE_8_W_Large.png</bgimagepathLarge>
    <bgimagepathSmall>bg_PRE_8_W_Small.png</bgimagepathSmall>
  </item>
  <item>
    <id>PCY0009</id>
    <colors>
      <color>W</color>
    </colors>
    <rarity>U</rarity>
    <cost>{1}{W}</cost>
    <type>ENC</type>
    <characteristics>
    </characteristics>
    <artist>Jeff Miracola</artist>
    <style>PRE_8</style>
    <imagePath>Flowering Field.jpg</imagePath>
    <bgimagepathLarge>bg_PRE_8_W_Large.png</bgimagepathLarge>
    <bgimagepathSmall>bg_PRE_8_W_Small.png</bgimagepathSmall>
  </item>
  <item>
    <id>PCY0010</id>
    <colors>
      <color>W</color>
    </colors>
    <rarity>U</rarity>
    <cost>{2}{W}</cost>
    <type>CRE</type>
    <characteristics>2/2</characteristics>
    <artist>Don Hazeltine</artist>
    <style>PRE_8</style>
    <imagePath>Glittering Lion.jpg</imagePath>
    <bgimagepathLarge>bg_PRE_8_W_Large.png</bgimagepathLarge>
    <bgimagepathSmall>bg_PRE_8_W_Small.png</bgimagepathSmall>
  </item>
  <item>
    <id>PCY0011</id>
    <colors>
      <color>W</color>
    </colors>
    <rarity>C</rarity>
    <cost>{W}</cost>
    <type>CRE</type>
    <characteristics>1/1</characteristics>
    <artist>Dan Frazier</artist>
    <style>PRE_8</style>
    <imagePath>Glittering Lynx.jpg</imagePath>
    <bgimagepathLarge>bg_PRE_8_W_Large.png</bgimagepathLarge>
    <bgimagepathSmall>bg_PRE_8_W_Small.png</bgimagepathSmall>
  </item>
  <item>
    <id>PCY0012</id>
    <colors>
      <color>W</color>
    </colors>
    <rarity>R</rarity>
    <cost>{3}{W}{W}</cost>
    <type>CRE</type>
    <characteristics>3/3</characteristics>
    <artist>Christopher Moeller</artist>
    <style>PRE_8</style>
    <imagePath>Jeweled Spirit.jpg</imagePath>
    <bgimagepathLarge>bg_PRE_8_W_Large.png</bgimagepathLarge>
    <bgimagepathSmall>bg_PRE_8_W_Small.png</bgimagepathSmall>
  </item>
  <item>
    <id>PCY0013</id>
    <colors>
      <color>W</color>
    </colors>
    <rarity>R</rarity>
    <cost>{3}{W}{W}</cost>
    <type>LCR</type>
    <characteristics>3/3</characteristics>
    <artist>Brom</artist>
    <style>PRE_8</style>
    <imagePath>Mageta the Lion.jpg</imagePath>
    <bgimagepathLarge>bg_PRE_8_W_Large.png</bgimagepathLarge>
    <bgimagepathSmall>bg_PRE_8_W_Small.png</bgimagepathSmall>
  </item>
  <item>
    <id>PCY0014</id>
    <colors>
      <color>W</color>
    </colors>
    <rarity>C</rarity>
    <cost>{1}{W}</cost>
    <type>ENC</type>
    <characteristics>
    </characteristics>
    <artist>Bradley Williams</artist>
    <style>PRE_8</style>
    <imagePath>Mageta's Boon.jpg</imagePath>
    <bgimagepathLarge>bg_PRE_8_W_Large.png</bgimagepathLarge>
    <bgimagepathSmall>bg_PRE_8_W_Small.png</bgimagepathSmall>
  </item>
  <item>
    <id>PCY0015</id>
    <colors>
      <color>W</color>
    </colors>
    <rarity>R</rarity>
    <cost>{2}{W}</cost>
    <type>CRE</type>
    <characteristics>2/1</characteristics>
    <artist>Nelson DeCastro</artist>
    <style>PRE_8</style>
    <imagePath>Mercenary Informer.jpg</imagePath>
    <bgimagepathLarge>bg_PRE_8_W_Large.png</bgimagepathLarge>
    <bgimagepathSmall>bg_PRE_8_W_Small.png</bgimagepathSmall>
  </item>
  <item>
    <id>PCY0016</id>
    <colors>
      <color>W</color>
    </colors>
    <rarity>C</rarity>
    <cost>{2}{W}</cost>
    <type>CRE</type>
    <characteristics>1/1</characteristics>
    <artist>D. Alexander Gregory</artist>
    <style>PRE_8</style>
    <imagePath>Mine Bearer.jpg</imagePath>
    <bgimagepathLarge>bg_PRE_8_W_Large.png</bgimagepathLarge>
    <bgimagepathSmall>bg_PRE_8_W_Small.png</bgimagepathSmall>
  </item>
  <item>
    <id>PCY0017</id>
    <colors>
      <color>W</color>
    </colors>
    <rarity>U</rarity>
    <cost>{3}{W}</cost>
    <type>INS</type>
    <characteristics>
    </characteristics>
    <artist>Dave Dorman</artist>
    <style>PRE_8</style>
    <imagePath>Mirror Strike.jpg</imagePath>
    <bgimagepathLarge>bg_PRE_8_W_Large.png</bgimagepathLarge>
    <bgimagepathSmall>bg_PRE_8_W_Small.png</bgimagepathSmall>
  </item>
  <item>
    <id>PCY0018</id>
    <colors>
      <color>W</color>
    </colors>
    <rarity>U</rarity>
    <cost>{2}{W}{W}</cost>
    <type>CRE</type>
    <characteristics>3/3</characteristics>
    <artist>Greg &amp; Tim Hildebrandt</artist>
    <style>PRE_8</style>
    <imagePath>Reveille Squad.jpg</imagePath>
    <bgimagepathLarge>bg_PRE_8_W_Large.png</bgimagepathLarge>
    <bgimagepathSmall>bg_PRE_8_W_Small.png</bgimagepathSmall>
  </item>
  <item>
    <id>PCY0019</id>
    <colors>
      <color>W</color>
    </colors>
    <rarity>C</rarity>
    <cost>{2}{W}{W}</cost>
    <type>ENC</type>
    <characteristics>
    </characteristics>
    <artist>Alan Pollack</artist>
    <style>PRE_8</style>
    <imagePath>Rhystic Circle.jpg</imagePath>
    <bgimagepathLarge>bg_PRE_8_W_Large.png</bgimagepathLarge>
    <bgimagepathSmall>bg_PRE_8_W_Small.png</bgimagepathSmall>
  </item>
  <item>
    <id>PCY0020</id>
    <colors>
      <color>W</color>
    </colors>
    <rarity>C</rarity>
    <cost>{1}{W}</cost>
    <type>INS</type>
    <characteristics>
    </characteristics>
    <artist>Kev Walker</artist>
    <style>PRE_8</style>
    <imagePath>Rhystic Shield.jpg</imagePath>
    <bgimagepathLarge>bg_PRE_8_W_Large.png</bgimagepathLarge>
    <bgimagepathSmall>bg_PRE_8_W_Small.png</bgimagepathSmall>
  </item>
  <item>
    <id>PCY0021</id>
    <colors>
      <color>W</color>
    </colors>
    <rarity>R</rarity>
    <cost>{2}{W}</cost>
    <type>ENC</type>
    <characteristics>
    </characteristics>
    <artist>Ben Thompson</artist>
    <style>PRE_8</style>
    <imagePath>Samite Sanctuary.jpg</imagePath>
    <bgimagepathLarge>bg_PRE_8_W_Large.png</bgimagepathLarge>
    <bgimagepathSmall>bg_PRE_8_W_Small.png</bgimagepathSmall>
  </item>
  <item>
    <id>PCY0022</id>
    <colors>
      <color>W</color>
    </colors>
    <rarity>R</rarity>
    <cost>{W}</cost>
    <type>ENC</type>
    <characteristics>
    </characteristics>
    <artist>Nelson DeCastro</artist>
    <style>PRE_8</style>
    <imagePath>Sheltering Prayers.jpg</imagePath>
    <bgimagepathLarge>bg_PRE_8_W_Large.png</bgimagepathLarge>
    <bgimagepathSmall>bg_PRE_8_W_Small.png</bgimagepathSmall>
  </item>
  <item>
    <id>PCY0023</id>
    <colors>
      <color>W</color>
    </colors>
    <rarity>U</rarity>
    <cost>{2}{W}</cost>
    <type>CRE</type>
    <characteristics>1/3</characteristics>
    <artist>Mike Ploog</artist>
    <style>PRE_8</style>
    <imagePath>Shield Dancer.jpg</imagePath>
    <bgimagepathLarge>bg_PRE_8_W_Large.png</bgimagepathLarge>
    <bgimagepathSmall>bg_PRE_8_W_Small.png</bgimagepathSmall>
  </item>
  <item>
    <id>PCY0024</id>
    <colors>
      <color>W</color>
    </colors>
    <rarity>C</rarity>
    <cost>{2}{W}</cost>
    <type>CRE</type>
    <characteristics>2/2</characteristics>
    <artist>Glen Angus</artist>
    <style>PRE_8</style>
    <imagePath>Soul Charmer.jpg</imagePath>
    <bgimagepathLarge>bg_PRE_8_W_Large.png</bgimagepathLarge>
    <bgimagepathSmall>bg_PRE_8_W_Small.png</bgimagepathSmall>
  </item>
  <item>
    <id>PCY0025</id>
    <colors>
      <color>W</color>
    </colors>
    <rarity>U</rarity>
    <cost>{1}{W}</cost>
    <type>CRE</type>
    <characteristics>1/2</characteristics>
    <artist>Roger Raupp</artist>
    <style>PRE_8</style>
    <imagePath>Sword Dancer.jpg</imagePath>
    <bgimagepathLarge>bg_PRE_8_W_Large.png</bgimagepathLarge>
    <bgimagepathSmall>bg_PRE_8_W_Small.png</bgimagepathSmall>
  </item>
  <item>
    <id>PCY0026</id>
    <colors>
      <color>W</color>
    </colors>
    <rarity>C</rarity>
    <cost>{3}{W}</cost>
    <type>CRE</type>
    <characteristics>2/3</characteristics>
    <artist>Greg &amp; Tim Hildebrandt</artist>
    <style>PRE_8</style>
    <imagePath>Trenching Steed.jpg</imagePath>
    <bgimagepathLarge>bg_PRE_8_W_Large.png</bgimagepathLarge>
    <bgimagepathSmall>bg_PRE_8_W_Small.png</bgimagepathSmall>
  </item>
  <item>
    <id>PCY0027</id>
    <colors>
      <color>W</color>
    </colors>
    <rarity>C</rarity>
    <cost>{2}{W}</cost>
    <type>CRE</type>
    <characteristics>1/2</characteristics>
    <artist>Terese Nielsen</artist>
    <style>PRE_8</style>
    <imagePath>Troubled Healer.jpg</imagePath>
    <bgimagepathLarge>bg_PRE_8_W_Large.png</bgimagepathLarge>
    <bgimagepathSmall>bg_PRE_8_W_Small.png</bgimagepathSmall>
  </item>
  <item>
    <id>PCY0028</id>
    <colors>
      <color>U</color>
    </colors>
    <rarity>R</rarity>
    <cost>{3}{U}{U}</cost>
    <type>LCR</type>
    <characteristics>3/3</characteristics>
    <artist>Mark Zug</artist>
    <style>PRE_8</style>
    <imagePath>Alexi, Zephyr Mage.jpg</imagePath>
    <bgimagepathLarge>bg_PRE_8_U_Large.png</bgimagepathLarge>
    <bgimagepathSmall>bg_PRE_8_U_Small.png</bgimagepathSmall>
  </item>
  <item>
    <id>PCY0029</id>
    <colors>
      <color>U</color>
    </colors>
    <rarity>C</rarity>
    <cost>{1}{U}</cost>
    <type>ENC</type>
    <characteristics>
    </characteristics>
    <artist>Alan Rabinowitz</artist>
    <style>PRE_8</style>
    <imagePath>Alexi's Cloak.jpg</imagePath>
    <bgimagepathLarge>bg_PRE_8_U_Large.png</bgimagepathLarge>
    <bgimagepathSmall>bg_PRE_8_U_Small.png</bgimagepathSmall>
  </item>
  <item>
    <id>PCY0030</id>
    <colors>
      <color>U</color>
    </colors>
    <rarity>R</rarity>
    <cost>{6}{U}{U}</cost>
    <type>CRE</type>
    <characteristics>5/6</characteristics>
    <artist>rk post</artist>
    <style>PRE_8</style>
    <imagePath>Avatar of Will.jpg</imagePath>
    <bgimagepathLarge>bg_PRE_8_U_Large.png</bgimagepathLarge>
    <bgimagepathSmall>bg_PRE_8_U_Small.png</bgimagepathSmall>
  </item>
  <item>
    <id>PCY0031</id>
    <colors>
      <color>U</color>
    </colors>
    <rarity>C</rarity>
    <cost>{4}{U}</cost>
    <type>CRE</type>
    <characteristics>3/3</characteristics>
    <artist>DiTerlizzi</artist>
    <style>PRE_8</style>
    <imagePath>Coastal Hornclaw.jpg</imagePath>
    <bgimagepathLarge>bg_PRE_8_U_Large.png</bgimagepathLarge>
    <bgimagepathSmall>bg_PRE_8_U_Small.png</bgimagepathSmall>
  </item>
  <item>
    <id>PCY0032</id>
    <colors>
      <color>U</color>
    </colors>
    <rarity>R</rarity>
    <cost>{7}{U}{U}</cost>
    <type>SOR</type>
    <characteristics>
    </characteristics>
    <artist>Tony Szczudlo</artist>
    <style>PRE_8</style>
    <imagePath>Denying Wind.jpg</imagePath>
    <bgimagepathLarge>bg_PRE_8_U_Large.png</bgimagepathLarge>
    <bgimagepathSmall>bg_PRE_8_U_Small.png</bgimagepathSmall>
  </item>
  <item>
    <id>PCY0033</id>
    <colors>
      <color>U</color>
    </colors>
    <rarity>U</rarity>
    <cost>{1}{U}</cost>
    <type>ENC</type>
    <characteristics>
    </characteristics>
    <artist>Terese Nielsen</artist>
    <style>PRE_8</style>
    <imagePath>Excavation.jpg</imagePath>
    <bgimagepathLarge>bg_PRE_8_U_Large.png</bgimagepathLarge>
    <bgimagepathSmall>bg_PRE_8_U_Small.png</bgimagepathSmall>
  </item>
  <item>
    <id>PCY0034</id>
    <colors>
      <color>U</color>
    </colors>
    <rarity>U</rarity>
    <cost>{2}{U}{U}</cost>
    <type>INS</type>
    <characteristics>
    </characteristics>
    <artist>Bradley Williams</artist>
    <style>PRE_8</style>
    <imagePath>Foil.jpg</imagePath>
    <bgimagepathLarge>bg_PRE_8_U_Large.png</bgimagepathLarge>
    <bgimagepathSmall>bg_PRE_8_U_Small.png</bgimagepathSmall>
  </item>
  <item>
    <id>PCY0035</id>
    <colors>
      <color>U</color>
    </colors>
    <rarity>C</rarity>
    <cost>{3}{U}</cost>
    <type>CRE</type>
    <characteristics>2/2</characteristics>
    <artist>Wayne England</artist>
    <style>PRE_8</style>
    <imagePath>Gulf Squid.jpg</imagePath>
    <bgimagepathLarge>bg_PRE_8_U_Large.png</bgimagepathLarge>
    <bgimagepathSmall>bg_PRE_8_U_Small.png</bgimagepathSmall>
  </item>
  <item>
    <id>PCY0036</id>
    <colors>
      <color>U</color>
    </colors>
    <rarity>C</rarity>
    <cost>{1}{U}</cost>
    <type>CRE</type>
    <characteristics>1/1</characteristics>
    <artist>Anthony S. Waters</artist>
    <style>PRE_8</style>
    <imagePath>Hazy Homunculus.jpg</imagePath>
    <bgimagepathLarge>bg_PRE_8_U_Large.png</bgimagepathLarge>
    <bgimagepathSmall>bg_PRE_8_U_Small.png</bgimagepathSmall>
  </item>
  <item>
    <id>PCY0037</id>
    <colors>
      <color>U</color>
    </colors>
    <rarity>R</rarity>
    <cost>{3}{U}{U}</cost>
    <type>ENC</type>
    <characteristics>
    </characteristics>
    <artist>Pete Venters</artist>
    <style>PRE_8</style>
    <imagePath>Heightened Awareness.jpg</imagePath>
    <bgimagepathLarge>bg_PRE_8_U_Large.png</bgimagepathLarge>
    <bgimagepathSmall>bg_PRE_8_U_Small.png</bgimagepathSmall>
  </item>
  <item>
    <id>PCY0038</id>
    <colors>
      <color>U</color>
    </colors>
    <rarity>U</rarity>
    <cost>{1}{U}</cost>
    <type>SOR</type>
    <characteristics>
    </characteristics>
    <artist>Mark Romanoski</artist>
    <style>PRE_8</style>
    <imagePath>Mana Vapors.jpg</imagePath>
    <bgimagepathLarge>bg_PRE_8_U_Large.png</bgimagepathLarge>
    <bgimagepathSmall>bg_PRE_8_U_Small.png</bgimagepathSmall>
  </item>
  <item>
    <id>PCY0039</id>
    <colors>
      <color>U</color>
    </colors>
    <rarity>R</rarity>
    <cost>{1}{U}</cost>
    <type>ENC</type>
    <characteristics>
    </characteristics>
    <artist>John Matson</artist>
    <style>PRE_8</style>
    <imagePath>Overburden.jpg</imagePath>
    <bgimagepathLarge>bg_PRE_8_U_Large.png</bgimagepathLarge>
    <bgimagepathSmall>bg_PRE_8_U_Small.png</bgimagepathSmall>
  </item>
  <item>
    <id>PCY0040</id>
    <colors>
      <color>U</color>
    </colors>
    <rarity>R</rarity>
    <cost>{1}{U}</cost>
    <type>SOR</type>
    <characteristics>
    </characteristics>
    <artist>Don Hazeltine</artist>
    <style>PRE_8</style>
    <imagePath>Psychic Theft.jpg</imagePath>
    <bgimagepathLarge>bg_PRE_8_U_Large.png</bgimagepathLarge>
    <bgimagepathSmall>bg_PRE_8_U_Small.png</bgimagepathSmall>
  </item>
  <item>
    <id>PCY0041</id>
    <colors>
      <color>U</color>
    </colors>
    <rarity>U</rarity>
    <cost>{2}{U}</cost>
    <type>CRE</type>
    <characteristics>1/6</characteristics>
    <artist>Matt Cavotta</artist>
    <style>PRE_8</style>
    <imagePath>Quicksilver Wall.jpg</imagePath>
    <bgimagepathLarge>bg_PRE_8_U_Large.png</bgimagepathLarge>
    <bgimagepathSmall>bg_PRE_8_U_Small.png</bgimagepathSmall>
  </item>
  <item>
    <id>PCY0042</id>
    <colors>
      <color>U</color>
    </colors>
    <rarity>C</rarity>
    <cost>{2}{U}</cost>
    <type>INS</type>
    <characteristics>
    </characteristics>
    <artist>Matt Cavotta</artist>
    <style>PRE_8</style>
    <imagePath>Rethink.jpg</imagePath>
    <bgimagepathLarge>bg_PRE_8_U_Large.png</bgimagepathLarge>
    <bgimagepathSmall>bg_PRE_8_U_Small.png</bgimagepathSmall>
  </item>
  <item>
    <id>PCY0043</id>
    <colors>
      <color>U</color>
    </colors>
    <rarity>C</rarity>
    <cost>{2}{U}</cost>
    <type>ENC</type>
    <characteristics>
    </characteristics>
    <artist>Pete Venters</artist>
    <style>PRE_8</style>
    <imagePath>Rhystic Deluge.jpg</imagePath>
    <bgimagepathLarge>bg_PRE_8_U_Large.png</bgimagepathLarge>
    <bgimagepathSmall>bg_PRE_8_U_Small.png</bgimagepathSmall>
  </item>
  <item>
    <id>PCY0044</id>
    <colors>
      <color>U</color>
    </colors>
    <rarity>U</rarity>
    <cost>{2}{U}{U}</cost>
    <type>SOR</type>
    <characteristics>
    </characteristics>
    <artist>Roger Raupp</artist>
    <style>PRE_8</style>
    <imagePath>Rhystic Scrying.jpg</imagePath>
    <bgimagepathLarge>bg_PRE_8_U_Large.png</bgimagepathLarge>
    <bgimagepathSmall>bg_PRE_8_U_Small.png</bgimagepathSmall>
  </item>
  <item>
    <id>PCY0045</id>
    <colors>
      <color>U</color>
    </colors>
    <rarity>C</rarity>
    <cost>{2}{U}</cost>
    <type>ENC</type>
    <characteristics>
    </characteristics>
    <artist>Terese Nielsen</artist>
    <style>PRE_8</style>
    <imagePath>Rhystic Study.jpg</imagePath>
    <bgimagepathLarge>bg_PRE_8_U_Large.png</bgimagepathLarge>
    <bgimagepathSmall>bg_PRE_8_U_Small.png</bgimagepathSmall>
  </item>
  <item>
    <id>PCY0046</id>
    <colors>
      <color>U</color>
    </colors>
    <rarity>C</rarity>
    <cost>{1}{U}{U}</cost>
    <type>CRE</type>
    <characteristics>2/3</characteristics>
    <artist>Mark Zug</artist>
    <style>PRE_8</style>
    <imagePath>Ribbon Snake.jpg</imagePath>
    <bgimagepathLarge>bg_PRE_8_U_Large.png</bgimagepathLarge>
    <bgimagepathSmall>bg_PRE_8_U_Small.png</bgimagepathSmall>
  </item>
  <item>
    <id>PCY0047</id>
    <colors>
      <color>U</color>
    </colors>
    <rarity>R</rarity>
    <cost>{4}{U}{U}{U}</cost>
    <type>CRE</type>
    <characteristics>4/4</characteristics>
    <artist>Dana Knutson</artist>
    <style>PRE_8</style>
    <imagePath>Shrouded Serpent.jpg</imagePath>
    <bgimagepathLarge>bg_PRE_8_U_Large.png</bgimagepathLarge>
    <bgimagepathSmall>bg_PRE_8_U_Small.png</bgimagepathSmall>
  </item>
  <item>
    <id>PCY0048</id>
    <colors>
      <color>U</color>
    </colors>
    <rarity>U</rarity>
    <cost>{3}{U}{U}</cost>
    <type>CRE</type>
    <characteristics>3/3</characteristics>
    <artist>Michael Sutfin</artist>
    <style>PRE_8</style>
    <imagePath>Spiketail Drake.jpg</imagePath>
    <bgimagepathLarge>bg_PRE_8_U_Large.png</bgimagepathLarge>
    <bgimagepathSmall>bg_PRE_8_U_Small.png</bgimagepathSmall>
  </item>
  <item>
    <id>PCY0049</id>
    <colors>
      <color>U</color>
    </colors>
    <rarity>C</rarity>
    <cost>{1}{U}</cost>
    <type>CRE</type>
    <characteristics>1/1</characteristics>
    <artist>Greg Staples</artist>
    <style>PRE_8</style>
    <imagePath>Spiketail Hatchling.jpg</imagePath>
    <bgimagepathLarge>bg_PRE_8_U_Large.png</bgimagepathLarge>
    <bgimagepathSmall>bg_PRE_8_U_Small.png</bgimagepathSmall>
  </item>
  <item>
    <id>PCY0050</id>
    <colors>
      <color>U</color>
    </colors>
    <rarity>C</rarity>
    <cost>{3}{U}</cost>
    <type>CRE</type>
    <characteristics>2/1</characteristics>
    <artist>Aaron Boyd</artist>
    <style>PRE_8</style>
    <imagePath>Stormwatch Eagle.jpg</imagePath>
    <bgimagepathLarge>bg_PRE_8_U_Large.png</bgimagepathLarge>
    <bgimagepathSmall>bg_PRE_8_U_Small.png</bgimagepathSmall>
  </item>
  <item>
    <id>PCY0051</id>
    <colors>
      <color>U</color>
    </colors>
    <rarity>U</rarity>
    <cost>{1}{U}</cost>
    <type>ENC</type>
    <characteristics>
    </characteristics>
    <artist>Donato Giancola</artist>
    <style>PRE_8</style>
    <imagePath>Sunken Field.jpg</imagePath>
    <bgimagepathLarge>bg_PRE_8_U_Large.png</bgimagepathLarge>
    <bgimagepathSmall>bg_PRE_8_U_Small.png</bgimagepathSmall>
  </item>
  <item>
    <id>PCY0052</id>
    <colors>
      <color>U</color>
    </colors>
    <rarity>R</rarity>
    <cost>{2}{U}{U}</cost>
    <type>CRE</type>
    <characteristics>3/4</characteristics>
    <artist>Adam Rex</artist>
    <style>PRE_8</style>
    <imagePath>Troublesome Spirit.jpg</imagePath>
    <bgimagepathLarge>bg_PRE_8_U_Large.png</bgimagepathLarge>
    <bgimagepathSmall>bg_PRE_8_U_Small.png</bgimagepathSmall>
  </item>
  <item>
    <id>PCY0053</id>
    <colors>
      <color>U</color>
    </colors>
    <rarity>U</rarity>
    <cost>{3}{U}</cost>
    <type>CRE</type>
    <characteristics>3/3</characteristics>
    <artist>Brian Snoddy</artist>
    <style>PRE_8</style>
    <imagePath>Windscouter.jpg</imagePath>
    <bgimagepathLarge>bg_PRE_8_U_Large.png</bgimagepathLarge>
    <bgimagepathSmall>bg_PRE_8_U_Small.png</bgimagepathSmall>
  </item>
  <item>
    <id>PCY0054</id>
    <colors>
      <color>U</color>
    </colors>
    <rarity>C</rarity>
    <cost>{U}{U}</cost>
    <type>INS</type>
    <characteristics>
    </characteristics>
    <artist>Adam Rex</artist>
    <style>PRE_8</style>
    <imagePath>Withdraw.jpg</imagePath>
    <bgimagepathLarge>bg_PRE_8_U_Large.png</bgimagepathLarge>
    <bgimagepathSmall>bg_PRE_8_U_Small.png</bgimagepathSmall>
  </item>
  <item>
    <id>PCY0055</id>
    <colors>
      <color>B</color>
    </colors>
    <rarity>C</rarity>
    <cost>{1}{B}</cost>
    <type>CRE</type>
    <characteristics>1/1</characteristics>
    <artist>Donato Giancola</artist>
    <style>PRE_8</style>
    <imagePath>Agent of Shauku.jpg</imagePath>
    <bgimagepathLarge>bg_PRE_8_B_Large.png</bgimagepathLarge>
    <bgimagepathSmall>bg_PRE_8_B_Small.png</bgimagepathSmall>
  </item>
  <item>
    <id>PCY0056</id>
    <colors>
      <color>B</color>
    </colors>
    <rarity>R</rarity>
    <cost>{6}{B}{B}</cost>
    <type>CRE</type>
    <characteristics>6/5</characteristics>
    <artist>rk post</artist>
    <style>PRE_8</style>
    <imagePath>Avatar of Woe.jpg</imagePath>
    <bgimagepathLarge>bg_PRE_8_B_Large.png</bgimagepathLarge>
    <bgimagepathSmall>bg_PRE_8_B_Small.png</bgimagepathSmall>
  </item>
  <item>
    <id>PCY0057</id>
    <colors>
      <color>B</color>
    </colors>
    <rarity>R</rarity>
    <cost>{3}{B}{B}</cost>
    <type>CRE</type>
    <characteristics>5/4</characteristics>
    <artist>Glen Angus</artist>
    <style>PRE_8</style>
    <imagePath>Bog Elemental.jpg</imagePath>
    <bgimagepathLarge>bg_PRE_8_B_Large.png</bgimagepathLarge>
    <bgimagepathSmall>bg_PRE_8_B_Small.png</bgimagepathSmall>
  </item>
  <item>
    <id>PCY0058</id>
    <colors>
      <color>B</color>
    </colors>
    <rarity>C</rarity>
    <cost>{2}{B}</cost>
    <type>CRE</type>
    <characteristics>1/1</characteristics>
    <artist>Brian Snoddy</artist>
    <style>PRE_8</style>
    <imagePath>Bog Glider.jpg</imagePath>
    <bgimagepathLarge>bg_PRE_8_B_Large.png</bgimagepathLarge>
    <bgimagepathSmall>bg_PRE_8_B_Small.png</bgimagepathSmall>
  </item>
  <item>
    <id>PCY0059</id>
    <colors>
      <color>B</color>
    </colors>
    <rarity>U</rarity>
    <cost>{2}{B}</cost>
    <type>CRE</type>
    <characteristics>1/1</characteristics>
    <artist>Ron Spears</artist>
    <style>PRE_8</style>
    <imagePath>Chilling Apparition.jpg</imagePath>
    <bgimagepathLarge>bg_PRE_8_B_Large.png</bgimagepathLarge>
    <bgimagepathSmall>bg_PRE_8_B_Small.png</bgimagepathSmall>
  </item>
  <item>
    <id>PCY0060</id>
    <colors>
      <color>B</color>
    </colors>
    <rarity>R</rarity>
    <cost>{3}{B}{B}</cost>
    <type>CRE</type>
    <characteristics>3/3</characteristics>
    <artist>Arnie Swekel</artist>
    <style>PRE_8</style>
    <imagePath>Coffin Puppets.jpg</imagePath>
    <bgimagepathLarge>bg_PRE_8_B_Large.png</bgimagepathLarge>
    <bgimagepathSmall>bg_PRE_8_B_Small.png</bgimagepathSmall>
  </item>
  <item>
    <id>PCY0061</id>
    <colors>
      <color>B</color>
    </colors>
    <rarity>C</rarity>
    <cost>{2}{B}</cost>
    <type>CRE</type>
    <characteristics>2/2</characteristics>
    <artist>David Martin</artist>
    <style>PRE_8</style>
    <imagePath>Death Charmer.jpg</imagePath>
    <bgimagepathLarge>bg_PRE_8_B_Large.png</bgimagepathLarge>
    <bgimagepathSmall>bg_PRE_8_B_Small.png</bgimagepathSmall>
  </item>
  <item>
    <id>PCY0062</id>
    <colors>
      <color>B</color>
    </colors>
    <rarity>C</rarity>
    <cost>{3}{B}</cost>
    <type>SOR</type>
    <characteristics>
    </characteristics>
    <artist>Scott M. Fischer</artist>
    <style>PRE_8</style>
    <imagePath>Despoil.jpg</imagePath>
    <bgimagepathLarge>bg_PRE_8_B_Large.png</bgimagepathLarge>
    <bgimagepathSmall>bg_PRE_8_B_Small.png</bgimagepathSmall>
  </item>
  <item>
    <id>PCY0063</id>
    <colors>
      <color>B</color>
    </colors>
    <rarity>U</rarity>
    <cost>{2}{B}</cost>
    <type>ENC</type>
    <characteristics>
    </characteristics>
    <artist>Pete Venters</artist>
    <style>PRE_8</style>
    <imagePath>Endbringer's Revel.jpg</imagePath>
    <bgimagepathLarge>bg_PRE_8_B_Large.png</bgimagepathLarge>
    <bgimagepathSmall>bg_PRE_8_B_Small.png</bgimagepathSmall>
  </item>
  <item>
    <id>PCY0064</id>
    <colors>
      <color>B</color>
    </colors>
    <rarity>C</rarity>
    <cost>{3}{B}</cost>
    <type>CRE</type>
    <characteristics>3/2</characteristics>
    <artist>Edward P. Beard, Jr.</artist>
    <style>PRE_8</style>
    <imagePath>Fen Stalker.jpg</imagePath>
    <bgimagepathLarge>bg_PRE_8_B_Large.png</bgimagepathLarge>
    <bgimagepathSmall>bg_PRE_8_B_Small.png</bgimagepathSmall>
  </item>
  <item>
    <id>PCY0065</id>
    <colors>
      <color>B</color>
    </colors>
    <rarity>C</rarity>
    <cost>{3}{B}</cost>
    <type>SOR</type>
    <characteristics>
    </characteristics>
    <artist>Matthew D. Wilson</artist>
    <style>PRE_8</style>
    <imagePath>Flay.jpg</imagePath>
    <bgimagepathLarge>bg_PRE_8_B_Large.png</bgimagepathLarge>
    <bgimagepathSmall>bg_PRE_8_B_Small.png</bgimagepathSmall>
  </item>
  <item>
    <id>PCY0066</id>
    <colors>
      <color>B</color>
    </colors>
    <rarity>R</rarity>
    <cost>{3}{B}{B}</cost>
    <type>LCR</type>
    <characteristics>3/3</characteristics>
    <artist>Brom</artist>
    <style>PRE_8</style>
    <imagePath>Greel, Mind Raker.jpg</imagePath>
    <bgimagepathLarge>bg_PRE_8_B_Large.png</bgimagepathLarge>
    <bgimagepathSmall>bg_PRE_8_B_Small.png</bgimagepathSmall>
  </item>
  <item>
    <id>PCY0067</id>
    <colors>
      <color>B</color>
    </colors>
    <rarity>C</rarity>
    <cost>{1}{B}</cost>
    <type>ENC</type>
    <characteristics>
    </characteristics>
    <artist>Chippy</artist>
    <style>PRE_8</style>
    <imagePath>Greel's Caress.jpg</imagePath>
    <bgimagepathLarge>bg_PRE_8_B_Large.png</bgimagepathLarge>
    <bgimagepathSmall>bg_PRE_8_B_Small.png</bgimagepathSmall>
  </item>
  <item>
    <id>PCY0068</id>
    <colors>
      <color>B</color>
    </colors>
    <rarity>R</rarity>
    <cost>{4}{B}{B}</cost>
    <type>ENC</type>
    <characteristics>
    </characteristics>
    <artist>Ron Spencer</artist>
    <style>PRE_8</style>
    <imagePath>Infernal Genesis.jpg</imagePath>
    <bgimagepathLarge>bg_PRE_8_B_Large.png</bgimagepathLarge>
    <bgimagepathSmall>bg_PRE_8_B_Small.png</bgimagepathSmall>
  </item>
  <item>
    <id>PCY0069</id>
    <colors>
      <color>B</color>
    </colors>
    <rarity>U</rarity>
    <cost>{1}{B}</cost>
    <type>CRE</type>
    <characteristics>1/1</characteristics>
    <artist>Ray Lago</artist>
    <style>PRE_8</style>
    <imagePath>Nakaya Shade.jpg</imagePath>
    <bgimagepathLarge>bg_PRE_8_B_Large.png</bgimagepathLarge>
    <bgimagepathSmall>bg_PRE_8_B_Small.png</bgimagepathSmall>
  </item>
  <item>
    <id>PCY0070</id>
    <colors>
      <color>B</color>
    </colors>
    <rarity>U</rarity>
    <cost>{1}{B}{B}</cost>
    <type>ENC</type>
    <characteristics>
    </characteristics>
    <artist>Eric Peterson</artist>
    <style>PRE_8</style>
    <imagePath>Noxious Field.jpg</imagePath>
    <bgimagepathLarge>bg_PRE_8_B_Large.png</bgimagepathLarge>
    <bgimagepathSmall>bg_PRE_8_B_Small.png</bgimagepathSmall>
  </item>
  <item>
    <id>PCY0071</id>
    <colors>
      <color>B</color>
    </colors>
    <rarity>U</rarity>
    <cost>{3}{B}</cost>
    <type>SOR</type>
    <characteristics>
    </characteristics>
    <artist>Quinton Hoover</artist>
    <style>PRE_8</style>
    <imagePath>Outbreak.jpg</imagePath>
    <bgimagepathLarge>bg_PRE_8_B_Large.png</bgimagepathLarge>
    <bgimagepathSmall>bg_PRE_8_B_Small.png</bgimagepathSmall>
  </item>
  <item>
    <id>PCY0072</id>
    <colors>
      <color>B</color>
    </colors>
    <rarity>U</rarity>
    <cost>{2}{B}{B}</cost>
    <type>CRE</type>
    <characteristics>4/3</characteristics>
    <artist>Thomas Gianni</artist>
    <style>PRE_8</style>
    <imagePath>Pit Raptor.jpg</imagePath>
    <bgimagepathLarge>bg_PRE_8_B_Large.png</bgimagepathLarge>
    <bgimagepathSmall>bg_PRE_8_B_Small.png</bgimagepathSmall>
  </item>
  <item>
    <id>PCY0073</id>
    <colors>
      <color>B</color>
    </colors>
    <rarity>C</rarity>
    <cost>{1}{B}</cost>
    <type>CRE</type>
    <characteristics>1/1</characteristics>
    <artist>David Martin</artist>
    <style>PRE_8</style>
    <imagePath>Plague Fiend.jpg</imagePath>
    <bgimagepathLarge>bg_PRE_8_B_Large.png</bgimagepathLarge>
    <bgimagepathSmall>bg_PRE_8_B_Small.png</bgimagepathSmall>
  </item>
  <item>
    <id>PCY0074</id>
    <colors>
      <color>B</color>
    </colors>
    <rarity>R</rarity>
    <cost>{7}{B}{B}</cost>
    <type>SOR</type>
    <characteristics>
    </characteristics>
    <artist>Alan Pollack</artist>
    <style>PRE_8</style>
    <imagePath>Plague Wind.jpg</imagePath>
    <bgimagepathLarge>bg_PRE_8_B_Large.png</bgimagepathLarge>
    <bgimagepathSmall>bg_PRE_8_B_Small.png</bgimagepathSmall>
  </item>
  <item>
    <id>PCY0075</id>
    <colors>
      <color>B</color>
    </colors>
    <rarity>R</rarity>
    <cost>{2}{B}</cost>
    <type>CRE</type>
    <characteristics>1/2</characteristics>
    <artist>Scott M. Fischer</artist>
    <style>PRE_8</style>
    <imagePath>Rebel Informer.jpg</imagePath>
    <bgimagepathLarge>bg_PRE_8_B_Large.png</bgimagepathLarge>
    <bgimagepathSmall>bg_PRE_8_B_Small.png</bgimagepathSmall>
  </item>
  <item>
    <id>PCY0076</id>
    <colors>
      <color>B</color>
    </colors>
    <rarity>U</rarity>
    <cost>{3}{B}{B}</cost>
    <type>SOR</type>
    <characteristics>
    </characteristics>
    <artist>Ron Spencer</artist>
    <style>PRE_8</style>
    <imagePath>Rhystic Syphon.jpg</imagePath>
    <bgimagepathLarge>bg_PRE_8_B_Large.png</bgimagepathLarge>
    <bgimagepathSmall>bg_PRE_8_B_Small.png</bgimagepathSmall>
  </item>
  <item>
    <id>PCY0077</id>
    <colors>
      <color>B</color>
    </colors>
    <rarity>R</rarity>
    <cost>{2}{B}</cost>
    <type>SOR</type>
    <characteristics>
    </characteristics>
    <artist>Dan Frazier</artist>
    <style>PRE_8</style>
    <imagePath>Rhystic Tutor.jpg</imagePath>
    <bgimagepathLarge>bg_PRE_8_B_Large.png</bgimagepathLarge>
    <bgimagepathSmall>bg_PRE_8_B_Small.png</bgimagepathSmall>
  </item>
  <item>
    <id>PCY0078</id>
    <colors>
      <color>B</color>
    </colors>
    <rarity>C</rarity>
    <cost>{X}{B}</cost>
    <type>SOR</type>
    <characteristics>
    </characteristics>
    <artist>Daren Bader</artist>
    <style>PRE_8</style>
    <imagePath>Soul Strings.jpg</imagePath>
    <bgimagepathLarge>bg_PRE_8_B_Large.png</bgimagepathLarge>
    <bgimagepathSmall>bg_PRE_8_B_Small.png</bgimagepathSmall>
  </item>
  <item>
    <id>PCY0079</id>
    <colors>
      <color>B</color>
    </colors>
    <rarity>C</rarity>
    <cost>{1}{B}</cost>
    <type>INS</type>
    <characteristics>
    </characteristics>
    <artist>D. Alexander Gregory</artist>
    <style>PRE_8</style>
    <imagePath>Steal Strength.jpg</imagePath>
    <bgimagepathLarge>bg_PRE_8_B_Large.png</bgimagepathLarge>
    <bgimagepathSmall>bg_PRE_8_B_Small.png</bgimagepathSmall>
  </item>
  <item>
    <id>PCY0080</id>
    <colors>
      <color>B</color>
    </colors>
    <rarity>U</rarity>
    <cost>{2}{B}</cost>
    <type>CRE</type>
    <characteristics>2/4</characteristics>
    <artist>Marc Fishman</artist>
    <style>PRE_8</style>
    <imagePath>Wall of Vipers.jpg</imagePath>
    <bgimagepathLarge>bg_PRE_8_B_Large.png</bgimagepathLarge>
    <bgimagepathSmall>bg_PRE_8_B_Small.png</bgimagepathSmall>
  </item>
  <item>
    <id>PCY0081</id>
    <colors>
      <color>B</color>
    </colors>
    <rarity>C</rarity>
    <cost>{1}{B}</cost>
    <type>CRE</type>
    <characteristics>2/2</characteristics>
    <artist>Mark Tedin</artist>
    <style>PRE_8</style>
    <imagePath>Whipstitched Zombie.jpg</imagePath>
    <bgimagepathLarge>bg_PRE_8_B_Large.png</bgimagepathLarge>
    <bgimagepathSmall>bg_PRE_8_B_Small.png</bgimagepathSmall>
  </item>
  <item>
    <id>PCY0082</id>
    <colors>
      <color>R</color>
    </colors>
    <rarity>R</rarity>
    <cost>{6}{R}{R}</cost>
    <type>CRE</type>
    <characteristics>6/6</characteristics>
    <artist>rk post</artist>
    <style>PRE_8</style>
    <imagePath>Avatar of Fury.jpg</imagePath>
    <bgimagepathLarge>bg_PRE_8_R_Large.png</bgimagepathLarge>
    <bgimagepathSmall>bg_PRE_8_R_Small.png</bgimagepathSmall>
  </item>
  <item>
    <id>PCY0083</id>
    <colors>
      <color>R</color>
    </colors>
    <rarity>U</rarity>
    <cost>{2}{R}{R}</cost>
    <type>ENC</type>
    <characteristics>
    </characteristics>
    <artist>Carl Critchlow</artist>
    <style>PRE_8</style>
    <imagePath>Barbed Field.jpg</imagePath>
    <bgimagepathLarge>bg_PRE_8_R_Large.png</bgimagepathLarge>
    <bgimagepathSmall>bg_PRE_8_R_Small.png</bgimagepathSmall>
  </item>
  <item>
    <id>PCY0084</id>
    <colors>
      <color>R</color>
    </colors>
    <rarity>C</rarity>
    <cost>{R}</cost>
    <type>CRE</type>
    <characteristics>2/2</characteristics>
    <artist>Scott M. Fischer</artist>
    <style>PRE_8</style>
    <imagePath>Branded Brawlers.jpg</imagePath>
    <bgimagepathLarge>bg_PRE_8_R_Large.png</bgimagepathLarge>
    <bgimagepathSmall>bg_PRE_8_R_Small.png</bgimagepathSmall>
  </item>
  <item>
    <id>PCY0085</id>
    <colors>
      <color>R</color>
    </colors>
    <rarity>U</rarity>
    <cost>{R}</cost>
    <type>ENC</type>
    <characteristics>
    </characteristics>
    <artist>Val Mayerik</artist>
    <style>PRE_8</style>
    <imagePath>Brutal Suppression.jpg</imagePath>
    <bgimagepathLarge>bg_PRE_8_R_Large.png</bgimagepathLarge>
    <bgimagepathSmall>bg_PRE_8_R_Small.png</bgimagepathSmall>
  </item>
  <item>
    <id>PCY0086</id>
    <colors>
      <color>R</color>
    </colors>
    <rarity>U</rarity>
    <cost>{2}{R}</cost>
    <type>ENC</type>
    <characteristics>
    </characteristics>
    <artist>Darrell Riche</artist>
    <style>PRE_8</style>
    <imagePath>Citadel of Pain.jpg</imagePath>
    <bgimagepathLarge>bg_PRE_8_R_Large.png</bgimagepathLarge>
    <bgimagepathSmall>bg_PRE_8_R_Small.png</bgimagepathSmall>
  </item>
  <item>
    <id>PCY0087</id>
    <colors>
      <color>R</color>
    </colors>
    <rarity>C</rarity>
    <cost>{3}{R}{R}</cost>
    <type>SOR</type>
    <characteristics>
    </characteristics>
    <artist>Greg Staples</artist>
    <style>PRE_8</style>
    <imagePath>Devastate.jpg</imagePath>
    <bgimagepathLarge>bg_PRE_8_R_Large.png</bgimagepathLarge>
    <bgimagepathSmall>bg_PRE_8_R_Small.png</bgimagepathSmall>
  </item>
  <item>
    <id>PCY0088</id>
    <colors>
      <color>R</color>
    </colors>
    <rarity>C</rarity>
    <cost>{2}{R}</cost>
    <type>CRE</type>
    <characteristics>2/2</characteristics>
    <artist>Dave Dorman</artist>
    <style>PRE_8</style>
    <imagePath>Fault Riders.jpg</imagePath>
    <bgimagepathLarge>bg_PRE_8_R_Large.png</bgimagepathLarge>
    <bgimagepathSmall>bg_PRE_8_R_Small.png</bgimagepathSmall>
  </item>
  <item>
    <id>PCY0089</id>
    <colors>
      <color>R</color>
    </colors>
    <rarity>R</rarity>
    <cost>{3}{R}</cost>
    <type>CRE</type>
    <characteristics>5/2</characteristics>
    <artist>Dave Dorman</artist>
    <style>PRE_8</style>
    <imagePath>Fickle Efreet.jpg</imagePath>
    <bgimagepathLarge>bg_PRE_8_R_Large.png</bgimagepathLarge>
    <bgimagepathSmall>bg_PRE_8_R_Small.png</bgimagepathSmall>
  </item>
  <item>
    <id>PCY0090</id>
    <colors>
      <color>R</color>
    </colors>
    <rarity>U</rarity>
    <cost>{3}{R}</cost>
    <type>SOR</type>
    <characteristics>
    </characteristics>
    <artist>Mark Brill</artist>
    <style>PRE_8</style>
    <imagePath>Flameshot.jpg</imagePath>
    <bgimagepathLarge>bg_PRE_8_R_Large.png</bgimagepathLarge>
    <bgimagepathSmall>bg_PRE_8_R_Small.png</bgimagepathSmall>
  </item>
  <item>
    <id>PCY0091</id>
    <colors>
      <color>R</color>
    </colors>
    <rarity>C</rarity>
    <cost>{R}</cost>
    <type>INS</type>
    <characteristics>
    </characteristics>
    <artist>Eric Peterson</artist>
    <style>PRE_8</style>
    <imagePath>Inflame.jpg</imagePath>
    <bgimagepathLarge>bg_PRE_8_R_Large.png</bgimagepathLarge>
    <bgimagepathSmall>bg_PRE_8_R_Small.png</bgimagepathSmall>
  </item>
  <item>
    <id>PCY0092</id>
    <colors>
      <color>R</color>
    </colors>
    <rarity>U</rarity>
    <cost>{2}{R}</cost>
    <type>CRE</type>
    <characteristics>1/1</characteristics>
    <artist>Paolo Parente</artist>
    <style>PRE_8</style>
    <imagePath>Keldon Arsonist.jpg</imagePath>
    <bgimagepathLarge>bg_PRE_8_R_Large.png</bgimagepathLarge>
    <bgimagepathSmall>bg_PRE_8_R_Small.png</bgimagepathSmall>
  </item>
  <item>
    <id>PCY0093</id>
    <colors>
      <color>R</color>
    </colors>
    <rarity>C</rarity>
    <cost>{3}{R}</cost>
    <type>CRE</type>
    <characteristics>2/3</characteristics>
    <artist>Paolo Parente</artist>
    <style>PRE_8</style>
    <imagePath>Keldon Berserker.jpg</imagePath>
    <bgimagepathLarge>bg_PRE_8_R_Large.png</bgimagepathLarge>
    <bgimagepathSmall>bg_PRE_8_R_Small.png</bgimagepathSmall>
  </item>
  <item>
    <id>PCY0094</id>
    <colors>
      <color>R</color>
    </colors>
    <rarity>R</rarity>
    <cost>{3}{R}{R}</cost>
    <type>CRE</type>
    <characteristics>3/3</characteristics>
    <artist>Randy Gallegos</artist>
    <style>PRE_8</style>
    <imagePath>Keldon Firebombers.jpg</imagePath>
    <bgimagepathLarge>bg_PRE_8_R_Large.png</bgimagepathLarge>
    <bgimagepathSmall>bg_PRE_8_R_Small.png</bgimagepathSmall>
  </item>
  <item>
    <id>PCY0095</id>
    <colors>
      <color>R</color>
    </colors>
    <rarity>R</rarity>
    <cost>{3}{R}{R}</cost>
    <type>LCR</type>
    <characteristics>3/3</characteristics>
    <artist>Brom</artist>
    <style>PRE_8</style>
    <imagePath>Latulla, Keldon Overseer.jpg</imagePath>
    <bgimagepathLarge>bg_PRE_8_R_Large.png</bgimagepathLarge>
    <bgimagepathSmall>bg_PRE_8_R_Small.png</bgimagepathSmall>
  </item>
  <item>
    <id>PCY0096</id>
    <colors>
      <color>R</color>
    </colors>
    <rarity>C</rarity>
    <cost>{1}{R}</cost>
    <type>ENC</type>
    <characteristics>
    </characteristics>
    <artist>Ben Thompson</artist>
    <style>PRE_8</style>
    <imagePath>Latulla's Orders.jpg</imagePath>
    <bgimagepathLarge>bg_PRE_8_R_Large.png</bgimagepathLarge>
    <bgimagepathSmall>bg_PRE_8_R_Small.png</bgimagepathSmall>
  </item>
  <item>
    <id>PCY0097</id>
    <colors>
      <color>R</color>
    </colors>
    <rarity>U</rarity>
    <cost>{2}{R}{R}</cost>
    <type>CRE</type>
    <characteristics>6/4</characteristics>
    <artist>Rob Alexander</artist>
    <style>PRE_8</style>
    <imagePath>Lesser Gargadon.jpg</imagePath>
    <bgimagepathLarge>bg_PRE_8_R_Large.png</bgimagepathLarge>
    <bgimagepathSmall>bg_PRE_8_R_Small.png</bgimagepathSmall>
  </item>
  <item>
    <id>PCY0098</id>
    <colors>
      <color>R</color>
    </colors>
    <rarity>C</rarity>
    <cost>{2}{R}</cost>
    <type>SOR</type>
    <characteristics>
    </characteristics>
    <artist>Mike Ploog</artist>
    <style>PRE_8</style>
    <imagePath>Panic Attack.jpg</imagePath>
    <bgimagepathLarge>bg_PRE_8_R_Large.png</bgimagepathLarge>
    <bgimagepathSmall>bg_PRE_8_R_Small.png</bgimagepathSmall>
  </item>
  <item>
    <id>PCY0099</id>
    <colors>
      <color>R</color>
    </colors>
    <rarity>C</rarity>
    <cost>{2}{R}</cost>
    <type>INS</type>
    <characteristics>
    </characteristics>
    <artist>Roger Raupp</artist>
    <style>PRE_8</style>
    <imagePath>Rhystic Lightning.jpg</imagePath>
    <bgimagepathLarge>bg_PRE_8_R_Large.png</bgimagepathLarge>
    <bgimagepathSmall>bg_PRE_8_R_Small.png</bgimagepathSmall>
  </item>
  <item>
    <id>PCY0100</id>
    <colors>
      <color>R</color>
    </colors>
    <rarity>C</rarity>
    <cost>{2}{R}</cost>
    <type>CRE</type>
    <characteristics>1/2</characteristics>
    <artist>Chippy</artist>
    <style>PRE_8</style>
    <imagePath>Ridgeline Rager.jpg</imagePath>
    <bgimagepathLarge>bg_PRE_8_R_Large.png</bgimagepathLarge>
    <bgimagepathSmall>bg_PRE_8_R_Small.png</bgimagepathSmall>
  </item>
  <item>
    <id>PCY0101</id>
    <colors>
      <color>R</color>
    </colors>
    <rarity>U</rarity>
    <cost>{3}{R}{R}</cost>
    <type>CRE</type>
    <characteristics>3/3</characteristics>
    <artist>Andrew Goldhawk</artist>
    <style>PRE_8</style>
    <imagePath>Scoria Cat.jpg</imagePath>
    <bgimagepathLarge>bg_PRE_8_R_Large.png</bgimagepathLarge>
    <bgimagepathSmall>bg_PRE_8_R_Small.png</bgimagepathSmall>
  </item>
  <item>
    <id>PCY0102</id>
    <colors>
      <color>R</color>
    </colors>
    <rarity>R</rarity>
    <cost>{2}{R}</cost>
    <type>SOR</type>
    <characteristics>
    </characteristics>
    <artist>Mark Romanoski</artist>
    <style>PRE_8</style>
    <imagePath>Search for Survivors.jpg</imagePath>
    <bgimagepathLarge>bg_PRE_8_R_Large.png</bgimagepathLarge>
    <bgimagepathSmall>bg_PRE_8_R_Small.png</bgimagepathSmall>
  </item>
  <item>
    <id>PCY0103</id>
    <colors>
      <color>R</color>
    </colors>
    <rarity>R</rarity>
    <cost>{8}{R}</cost>
    <type>INS</type>
    <characteristics>
    </characteristics>
    <artist>John Matson</artist>
    <style>PRE_8</style>
    <imagePath>Searing Wind.jpg</imagePath>
    <bgimagepathLarge>bg_PRE_8_R_Large.png</bgimagepathLarge>
    <bgimagepathSmall>bg_PRE_8_R_Small.png</bgimagepathSmall>
  </item>
  <item>
    <id>PCY0104</id>
    <colors>
      <color>R</color>
    </colors>
    <rarity>C</rarity>
    <cost>{2}{R}</cost>
    <type>CRE</type>
    <characteristics>2/1</characteristics>
    <artist>Randy Gallegos</artist>
    <style>PRE_8</style>
    <imagePath>Spur Grappler.jpg</imagePath>
    <bgimagepathLarge>bg_PRE_8_R_Large.png</bgimagepathLarge>
    <bgimagepathSmall>bg_PRE_8_R_Small.png</bgimagepathSmall>
  </item>
  <item>
    <id>PCY0105</id>
    <colors>
      <color>R</color>
    </colors>
    <rarity>R</rarity>
    <cost>{2}{R}</cost>
    <type>ENC</type>
    <characteristics>
    </characteristics>
    <artist>Val Mayerik</artist>
    <style>PRE_8</style>
    <imagePath>Task Mage Assembly.jpg</imagePath>
    <bgimagepathLarge>bg_PRE_8_R_Large.png</bgimagepathLarge>
    <bgimagepathSmall>bg_PRE_8_R_Small.png</bgimagepathSmall>
  </item>
  <item>
    <id>PCY0106</id>
    <colors>
      <color>R</color>
    </colors>
    <rarity>R</rarity>
    <cost>{1}{R}</cost>
    <type>CRE</type>
    <characteristics>4/4</characteristics>
    <artist>Paolo Parente</artist>
    <style>PRE_8</style>
    <imagePath>Veteran Brawlers.jpg</imagePath>
    <bgimagepathLarge>bg_PRE_8_R_Large.png</bgimagepathLarge>
    <bgimagepathSmall>bg_PRE_8_R_Small.png</bgimagepathSmall>
  </item>
  <item>
    <id>PCY0107</id>
    <colors>
      <color>R</color>
    </colors>
    <rarity>U</rarity>
    <cost>{2}{R}</cost>
    <type>CRE</type>
    <characteristics>2/1</characteristics>
    <artist>Paolo Parente</artist>
    <style>PRE_8</style>
    <imagePath>Whip Sergeant.jpg</imagePath>
    <bgimagepathLarge>bg_PRE_8_R_Large.png</bgimagepathLarge>
    <bgimagepathSmall>bg_PRE_8_R_Small.png</bgimagepathSmall>
  </item>
  <item>
    <id>PCY0108</id>
    <colors>
      <color>R</color>
    </colors>
    <rarity>C</rarity>
    <cost>{2}{R}{R}</cost>
    <type>CRE</type>
    <characteristics>3/3</characteristics>
    <artist>Mark Zug</artist>
    <style>PRE_8</style>
    <imagePath>Zerapa Minotaur.jpg</imagePath>
    <bgimagepathLarge>bg_PRE_8_R_Large.png</bgimagepathLarge>
    <bgimagepathSmall>bg_PRE_8_R_Small.png</bgimagepathSmall>
  </item>
  <item>
    <id>PCY0109</id>
    <colors>
      <color>G</color>
    </colors>
    <rarity>R</rarity>
    <cost>{6}{G}{G}</cost>
    <type>CRE</type>
    <characteristics>8/8</characteristics>
    <artist>rk post</artist>
    <style>PRE_8</style>
    <imagePath>Avatar of Might.jpg</imagePath>
    <bgimagepathLarge>bg_PRE_8_G_Large.png</bgimagepathLarge>
    <bgimagepathSmall>bg_PRE_8_G_Small.png</bgimagepathSmall>
  </item>
  <item>
    <id>PCY0110</id>
    <colors>
      <color>G</color>
    </colors>
    <rarity>C</rarity>
    <cost>{3}{G}</cost>
    <type>SOR</type>
    <characteristics>
    </characteristics>
    <artist>Rebecca Guay</artist>
    <style>PRE_8</style>
    <imagePath>Calming Verse.jpg</imagePath>
    <bgimagepathLarge>bg_PRE_8_G_Large.png</bgimagepathLarge>
    <bgimagepathSmall>bg_PRE_8_G_Small.png</bgimagepathSmall>
  </item>
  <item>
    <id>PCY0111</id>
    <colors>
      <color>G</color>
    </colors>
    <rarity>U</rarity>
    <cost>{3}{G}</cost>
    <type>CRE</type>
    <characteristics>5/4</characteristics>
    <artist>Heather Hudson</artist>
    <style>PRE_8</style>
    <imagePath>Darba.jpg</imagePath>
    <bgimagepathLarge>bg_PRE_8_G_Large.png</bgimagepathLarge>
    <bgimagepathSmall>bg_PRE_8_G_Small.png</bgimagepathSmall>
  </item>
  <item>
    <id>PCY0112</id>
    <colors>
      <color>G</color>
    </colors>
    <rarity>R</rarity>
    <cost>{4}{G}{G}</cost>
    <type>ENC</type>
    <characteristics>
    </characteristics>
    <artist>Arnie Swekel</artist>
    <style>PRE_8</style>
    <imagePath>Dual Nature.jpg</imagePath>
    <bgimagepathLarge>bg_PRE_8_G_Large.png</bgimagepathLarge>
    <bgimagepathSmall>bg_PRE_8_G_Small.png</bgimagepathSmall>
  </item>
  <item>
    <id>PCY0113</id>
    <colors>
      <color>G</color>
    </colors>
    <rarity>R</rarity>
    <cost>{1}{G}</cost>
    <type>SOR</type>
    <characteristics>
    </characteristics>
    <artist>DiTerlizzi</artist>
    <style>PRE_8</style>
    <imagePath>Elephant Resurgence.jpg</imagePath>
    <bgimagepathLarge>bg_PRE_8_G_Large.png</bgimagepathLarge>
    <bgimagepathSmall>bg_PRE_8_G_Small.png</bgimagepathSmall>
  </item>
  <item>
    <id>PCY0114</id>
    <colors>
      <color>G</color>
    </colors>
    <rarity>R</rarity>
    <cost>{1}{G}</cost>
    <type>ENC</type>
    <characteristics>
    </characteristics>
    <artist>DiTerlizzi</artist>
    <style>PRE_8</style>
    <imagePath>Forgotten Harvest.jpg</imagePath>
    <bgimagepathLarge>bg_PRE_8_G_Large.png</bgimagepathLarge>
    <bgimagepathSmall>bg_PRE_8_G_Small.png</bgimagepathSmall>
  </item>
  <item>
    <id>PCY0115</id>
    <colors>
      <color>G</color>
    </colors>
    <rarity>R</rarity>
    <cost>{3}{G}{G}</cost>
    <type>LCR</type>
    <characteristics>3/3</characteristics>
    <artist>Matthew D. Wilson</artist>
    <style>PRE_8</style>
    <imagePath>Jolrael, Empress of Beasts.jpg</imagePath>
    <bgimagepathLarge>bg_PRE_8_G_Large.png</bgimagepathLarge>
    <bgimagepathSmall>bg_PRE_8_G_Small.png</bgimagepathSmall>
  </item>
  <item>
    <id>PCY0116</id>
    <colors>
      <color>G</color>
    </colors>
    <rarity>C</rarity>
    <cost>{1}{G}</cost>
    <type>ENC</type>
    <characteristics>
    </characteristics>
    <artist>Daren Bader</artist>
    <style>PRE_8</style>
    <imagePath>Jolrael's Favor.jpg</imagePath>
    <bgimagepathLarge>bg_PRE_8_G_Large.png</bgimagepathLarge>
    <bgimagepathSmall>bg_PRE_8_G_Small.png</bgimagepathSmall>
  </item>
  <item>
    <id>PCY0117</id>
    <colors>
      <color>G</color>
    </colors>
    <rarity>U</rarity>
    <cost>{2}{G}{G}</cost>
    <type>ENC</type>
    <characteristics>
    </characteristics>
    <artist>Andrew Goldhawk</artist>
    <style>PRE_8</style>
    <imagePath>Living Terrain.jpg</imagePath>
    <bgimagepathLarge>bg_PRE_8_G_Large.png</bgimagepathLarge>
    <bgimagepathSmall>bg_PRE_8_G_Small.png</bgimagepathSmall>
  </item>
  <item>
    <id>PCY0118</id>
    <colors>
      <color>G</color>
    </colors>
    <rarity>C</rarity>
    <cost>{G}</cost>
    <type>CRE</type>
    <characteristics>1/1</characteristics>
    <artist>Heather Hudson</artist>
    <style>PRE_8</style>
    <imagePath>Marsh Boa.jpg</imagePath>
    <bgimagepathLarge>bg_PRE_8_G_Large.png</bgimagepathLarge>
    <bgimagepathSmall>bg_PRE_8_G_Small.png</bgimagepathSmall>
  </item>
  <item>
    <id>PCY0119</id>
    <colors>
      <color>G</color>
    </colors>
    <rarity>R</rarity>
    <cost>{2}{G}{G}</cost>
    <type>CRE</type>
    <characteristics>6/5</characteristics>
    <artist>Greg Staples</artist>
    <style>PRE_8</style>
    <imagePath>Mungha Wurm.jpg</imagePath>
    <bgimagepathLarge>bg_PRE_8_G_Large.png</bgimagepathLarge>
    <bgimagepathSmall>bg_PRE_8_G_Small.png</bgimagepathSmall>
  </item>
  <item>
    <id>PCY0120</id>
    <colors>
      <color>G</color>
    </colors>
    <rarity>C</rarity>
    <cost>{1}{G}</cost>
    <type>CRE</type>
    <characteristics>2/1</characteristics>
    <artist>Matt Cavotta</artist>
    <style>PRE_8</style>
    <imagePath>Pygmy Razorback.jpg</imagePath>
    <bgimagepathLarge>bg_PRE_8_G_Large.png</bgimagepathLarge>
    <bgimagepathSmall>bg_PRE_8_G_Small.png</bgimagepathSmall>
  </item>
  <item>
    <id>PCY0121</id>
    <colors>
      <color>G</color>
    </colors>
    <rarity>C</rarity>
    <cost>{2}{G}</cost>
    <type>CRE</type>
    <characteristics>1/4</characteristics>
    <artist>Dana Knutson</artist>
    <style>PRE_8</style>
    <imagePath>Rib Cage Spider.jpg</imagePath>
    <bgimagepathLarge>bg_PRE_8_G_Large.png</bgimagepathLarge>
    <bgimagepathSmall>bg_PRE_8_G_Small.png</bgimagepathSmall>
  </item>
  <item>
    <id>PCY0122</id>
    <colors>
      <color>G</color>
    </colors>
    <rarity>U</rarity>
    <cost>{1}{G}</cost>
    <type>ENC</type>
    <characteristics>
    </characteristics>
    <artist>Glen Angus</artist>
    <style>PRE_8</style>
    <imagePath>Root Cage.jpg</imagePath>
    <bgimagepathLarge>bg_PRE_8_G_Large.png</bgimagepathLarge>
    <bgimagepathSmall>bg_PRE_8_G_Small.png</bgimagepathSmall>
  </item>
  <item>
    <id>PCY0123</id>
    <colors>
      <color>G</color>
    </colors>
    <rarity>C</rarity>
    <cost>{2}{G}</cost>
    <type>CRE</type>
    <characteristics>3/3</characteristics>
    <artist>Arnie Swekel</artist>
    <style>PRE_8</style>
    <imagePath>Silt Crawler.jpg</imagePath>
    <bgimagepathLarge>bg_PRE_8_G_Large.png</bgimagepathLarge>
    <bgimagepathSmall>bg_PRE_8_G_Small.png</bgimagepathSmall>
  </item>
  <item>
    <id>PCY0124</id>
    <colors>
      <color>G</color>
    </colors>
    <rarity>U</rarity>
    <cost>{3}{G}</cost>
    <type>INS</type>
    <characteristics>
    </characteristics>
    <artist>Ron Spencer</artist>
    <style>PRE_8</style>
    <imagePath>Snag.jpg</imagePath>
    <bgimagepathLarge>bg_PRE_8_G_Large.png</bgimagepathLarge>
    <bgimagepathSmall>bg_PRE_8_G_Small.png</bgimagepathSmall>
  </item>
  <item>
    <id>PCY0125</id>
    <colors>
      <color>G</color>
    </colors>
    <rarity>U</rarity>
    <cost>{3}{G}{G}</cost>
    <type>CRE</type>
    <characteristics>3/5</characteristics>
    <artist>Edward P. Beard, Jr.</artist>
    <style>PRE_8</style>
    <imagePath>Spitting Spider.jpg</imagePath>
    <bgimagepathLarge>bg_PRE_8_G_Large.png</bgimagepathLarge>
    <bgimagepathSmall>bg_PRE_8_G_Small.png</bgimagepathSmall>
  </item>
  <item>
    <id>PCY0126</id>
    <colors>
      <color>G</color>
    </colors>
    <rarity>C</rarity>
    <cost>{G}</cost>
    <type>CRE</type>
    <characteristics>1/1</characteristics>
    <artist>Donato Giancola</artist>
    <style>PRE_8</style>
    <imagePath>Spore Frog.jpg</imagePath>
    <bgimagepathLarge>bg_PRE_8_G_Large.png</bgimagepathLarge>
    <bgimagepathSmall>bg_PRE_8_G_Small.png</bgimagepathSmall>
  </item>
  <item>
    <id>PCY0127</id>
    <colors>
      <color>G</color>
    </colors>
    <rarity>R</rarity>
    <cost>{2}{G}{G}</cost>
    <type>CRE</type>
    <characteristics>2/2</characteristics>
    <artist>Carl Critchlow</artist>
    <style>PRE_8</style>
    <imagePath>Squirrel Wrangler.jpg</imagePath>
    <bgimagepathLarge>bg_PRE_8_G_Large.png</bgimagepathLarge>
    <bgimagepathSmall>bg_PRE_8_G_Small.png</bgimagepathSmall>
  </item>
  <item>
    <id>PCY0128</id>
    <colors>
      <color>G</color>
    </colors>
    <rarity>C</rarity>
    <cost>{3}{G}{G}</cost>
    <type>CRE</type>
    <characteristics>4/4</characteristics>
    <artist>Jeff Easley</artist>
    <style>PRE_8</style>
    <imagePath>Thresher Beast.jpg</imagePath>
    <bgimagepathLarge>bg_PRE_8_G_Large.png</bgimagepathLarge>
    <bgimagepathSmall>bg_PRE_8_G_Small.png</bgimagepathSmall>
  </item>
  <item>
    <id>PCY0129</id>
    <colors>
      <color>G</color>
    </colors>
    <rarity>C</rarity>
    <cost>{X}{G}</cost>
    <type>SOR</type>
    <characteristics>
    </characteristics>
    <artist>Mike Ploog</artist>
    <style>PRE_8</style>
    <imagePath>Thrive.jpg</imagePath>
    <bgimagepathLarge>bg_PRE_8_G_Large.png</bgimagepathLarge>
    <bgimagepathSmall>bg_PRE_8_G_Small.png</bgimagepathSmall>
  </item>
  <item>
    <id>PCY0130</id>
    <colors>
      <color>G</color>
    </colors>
    <rarity>U</rarity>
    <cost>{2}{G}</cost>
    <type>ENC</type>
    <characteristics>
    </characteristics>
    <artist>Ron Spears</artist>
    <style>PRE_8</style>
    <imagePath>Verdant Field.jpg</imagePath>
    <bgimagepathLarge>bg_PRE_8_G_Large.png</bgimagepathLarge>
    <bgimagepathSmall>bg_PRE_8_G_Small.png</bgimagepathSmall>
  </item>
  <item>
    <id>PCY0131</id>
    <colors>
      <color>G</color>
    </colors>
    <rarity>C</rarity>
    <cost>{4}{G}</cost>
    <type>CRE</type>
    <characteristics>4/3</characteristics>
    <artist>Tony Szczudlo</artist>
    <style>PRE_8</style>
    <imagePath>Vintara Elephant.jpg</imagePath>
    <bgimagepathLarge>bg_PRE_8_G_Large.png</bgimagepathLarge>
    <bgimagepathSmall>bg_PRE_8_G_Small.png</bgimagepathSmall>
  </item>
  <item>
    <id>PCY0132</id>
    <colors>
      <color>G</color>
    </colors>
    <rarity>U</rarity>
    <cost>{G}{G}</cost>
    <type>CRE</type>
    <characteristics>2/2</characteristics>
    <artist>Joel Biske</artist>
    <style>PRE_8</style>
    <imagePath>Vintara Snapper.jpg</imagePath>
    <bgimagepathLarge>bg_PRE_8_G_Large.png</bgimagepathLarge>
    <bgimagepathSmall>bg_PRE_8_G_Small.png</bgimagepathSmall>
  </item>
  <item>
    <id>PCY0133</id>
    <colors>
      <color>G</color>
    </colors>
    <rarity>R</rarity>
    <cost>{8}{G}</cost>
    <type>INS</type>
    <characteristics>
    </characteristics>
    <artist>Jeff Easley</artist>
    <style>PRE_8</style>
    <imagePath>Vitalizing Wind.jpg</imagePath>
    <bgimagepathLarge>bg_PRE_8_G_Large.png</bgimagepathLarge>
    <bgimagepathSmall>bg_PRE_8_G_Small.png</bgimagepathSmall>
  </item>
  <item>
    <id>PCY0134</id>
    <colors>
      <color>G</color>
    </colors>
    <rarity>C</rarity>
    <cost>{1}{G}</cost>
    <type>INS</type>
    <characteristics>
    </characteristics>
    <artist>Carl Critchlow</artist>
    <style>PRE_8</style>
    <imagePath>Wild Might.jpg</imagePath>
    <bgimagepathLarge>bg_PRE_8_G_Large.png</bgimagepathLarge>
    <bgimagepathSmall>bg_PRE_8_G_Small.png</bgimagepathSmall>
  </item>
  <item>
    <id>PCY0135</id>
    <colors>
      <color>G</color>
    </colors>
    <rarity>U</rarity>
    <cost>{2}{G}</cost>
    <type>SOR</type>
    <characteristics>
    </characteristics>
    <artist>Heather Hudson</artist>
    <style>PRE_8</style>
    <imagePath>Wing Storm.jpg</imagePath>
    <bgimagepathLarge>bg_PRE_8_G_Large.png</bgimagepathLarge>
    <bgimagepathSmall>bg_PRE_8_G_Small.png</bgimagepathSmall>
  </item>
  <item>
    <id>PCY0136</id>
    <colors>
      <color>A</color>
    </colors>
    <rarity>U</rarity>
    <cost>{3}</cost>
    <type>ART</type>
    <characteristics>
    </characteristics>
    <artist>Mark Tedin</artist>
    <style>PRE_8</style>
    <imagePath>Chimeric Idol.jpg</imagePath>
    <bgimagepathLarge>bg_PRE_8_A_Large.png</bgimagepathLarge>
    <bgimagepathSmall>bg_PRE_8_A_Small.png</bgimagepathSmall>
  </item>
  <item>
    <id>PCY0137</id>
    <colors>
      <color>A</color>
    </colors>
    <rarity>R</rarity>
    <cost>{5}</cost>
    <type>ARC</type>
    <characteristics>2/2</characteristics>
    <artist>Christopher Moeller</artist>
    <style>PRE_8</style>
    <imagePath>Copper-Leaf Angel.jpg</imagePath>
    <bgimagepathLarge>bg_PRE_8_A_Large.png</bgimagepathLarge>
    <bgimagepathSmall>bg_PRE_8_A_Small.png</bgimagepathSmall>
  </item>
  <item>
    <id>PCY0138</id>
    <colors>
      <color>A</color>
    </colors>
    <rarity>U</rarity>
    <cost>{4}</cost>
    <type>ARC</type>
    <characteristics>4/4</characteristics>
    <artist>Adam Rex</artist>
    <style>PRE_8</style>
    <imagePath>Hollow Warrior.jpg</imagePath>
    <bgimagepathLarge>bg_PRE_8_A_Large.png</bgimagepathLarge>
    <bgimagepathSmall>bg_PRE_8_A_Small.png</bgimagepathSmall>
  </item>
  <item>
    <id>PCY0139</id>
    <colors>
      <color>A</color>
    </colors>
    <rarity>R</rarity>
    <cost>{5}</cost>
    <type>ARC</type>
    <characteristics>0/3</characteristics>
    <artist>Kev Walker</artist>
    <style>PRE_8</style>
    <imagePath>Keldon Battlewagon.jpg</imagePath>
    <bgimagepathLarge>bg_PRE_8_A_Large.png</bgimagepathLarge>
    <bgimagepathSmall>bg_PRE_8_A_Small.png</bgimagepathSmall>
  </item>
  <item>
    <id>PCY0140</id>
    <colors>
      <color>A</color>
    </colors>
    <rarity>R</rarity>
    <cost>{6}</cost>
    <type>ART</type>
    <characteristics>
    </characteristics>
    <artist>Alan Rabinowitz</artist>
    <style>PRE_8</style>
    <imagePath>Well of Discovery.jpg</imagePath>
    <bgimagepathLarge>bg_PRE_8_A_Large.png</bgimagepathLarge>
    <bgimagepathSmall>bg_PRE_8_A_Small.png</bgimagepathSmall>
  </item>
  <item>
    <id>PCY0141</id>
    <colors>
      <color>A</color>
    </colors>
    <rarity>U</rarity>
    <cost>{4}</cost>
    <type>ART</type>
    <characteristics>
    </characteristics>
    <artist>Tom Wnerstrand</artist>
    <style>PRE_8</style>
    <imagePath>Well of Life.jpg</imagePath>
    <bgimagepathLarge>bg_PRE_8_A_Large.png</bgimagepathLarge>
    <bgimagepathSmall>bg_PRE_8_A_Small.png</bgimagepathSmall>
  </item>
  <item>
    <id>PCY0142</id>
    <colors>
      <color>A</color>
    </colors>
    <rarity>U</rarity>
    <cost>
    </cost>
    <type>LND</type>
    <characteristics>
    </characteristics>
    <artist>Rob Alexander</artist>
    <style>PRE_8</style>
    <imagePath>Rhystic Cave.jpg</imagePath>
    <bgimagepathLarge>bg_PRE_8_A_Large.png</bgimagepathLarge>
    <bgimagepathSmall>bg_PRE_8_A_Small.png</bgimagepathSmall>
  </item>
  <item>
    <id>PCY0143</id>
    <colors>
      <color>A</color>
    </colors>
    <rarity>R</rarity>
    <cost>
    </cost>
    <type>LND</type>
    <characteristics>
    </characteristics>
    <artist>Tom Wnerstrand</artist>
    <style>PRE_8</style>
    <imagePath>Wintermoon Mesa.jpg</imagePath>
    <bgimagepathLarge>bg_PRE_8_A_Large.png</bgimagepathLarge>
    <bgimagepathSmall>bg_PRE_8_A_Small.png</bgimagepathSmall>
  </item>
</cards>